gsession/__init__.py
gsession/gnome_favorite_apps_setup.py
gsession/launch_chrome_and_vscode.py
gsession/main.py
gsession/parsec_setup.py
gsession/session_setup.py
gsession/ssh_key_maknager.py
gsession-0.1.5.dist-info/METADATA
gsession-0.1.5.dist-info/WHEEL
gsession-0.1.5.dist-info/entry_points.txt
gsession-0.1.5.dist-info/top_level.txt
gsession-0.1.5.dist-info/RECORD
