Metadata-Version: 2.1
Name: gsession
Version: 0.1.5
Summary: Un package pour gerer les session de 42
Author: guiguito
